ernest/__init__.py
ernest/cli.py
ernest/correctors/__init__.py
ernest/correctors/_base.py
ernest/correctors/ansible_task.py
ernest/correctors/py.py
ernest/data/ernest.json
ernest/helpers/__init__.py
ernest/helpers/common.py
ernest/helpers/py.py
ernest/models/__init__.py
ernest/models/coll.py
ernest/models/factories.py
ernest/models/meta.py
ernest/models/filetypes/__init__.py
ernest/models/filetypes/_ansible.py
ernest/models/filetypes/_base.py
ernest/models/filetypes/_py.py
ernest-0.1.6.dist-info/LICENSE
ernest-0.1.6.dist-info/METADATA
ernest-0.1.6.dist-info/WHEEL
ernest-0.1.6.dist-info/entry_points.txt
ernest-0.1.6.dist-info/top_level.txt
ernest-0.1.6.dist-info/RECORD
