Metadata-Version: 2.1
Name: ernest
Version: 0.1.6
Summary: A CLI-based tool for making bulk changes to file text.
Home-page: https://github.com/alycejenni/ernest
Author: Alice Butcher
Author-email: alycejenni@gmail.com
License: MIT
Platform: UNKNOWN
Classifier: Development Status :: 3 - Alpha
Classifier: Programming Language :: Python :: 2
Classifier: Programming Language :: Python
Classifier: Programming Language :: Python :: 3
Classifier: Topic :: Utilities
Requires-Dist: click
Requires-Dist: redbaron
